[
    {
        "id":"1",
        "title":"Brave",
        "description": "In a Scottish kingdom, Princess Merida's rebellion sparks chaos. Seeking to undo a curse endangering her mother, she confronts challenges, relying on courage and family bonds. This animated adventure, rich in visuals and emotion, explores themes of independence and self-discovery in a captivating tale.",
        "distributor":"Walt Disney",
        "year":"2012",
        "runtime": "1hr 38min",
        "rating": "93% match",
        "poster": "https://cdn.shopify.com/s/files/1/0057/3728/3618/products/902ab8634000ca23e92055988de210e0_2b3ec72d-873c-48b7-85cf-e5ac68c42f69_500x749.jpg?v=1573587242",
        "background": "https://www.intofilm.org/intofilm-production/1341/scaledcropped/3000x1688/resources/1341/brave-ep-disney.jpg"

     },
    {
        "id": "2",
        "title": "Onward",
        "description": "Set in a suburban fantasy realm, two elf brothers embark on a quest to resurrect their deceased father using a rare magical artifact, weaving a tale of humor, brotherhood, and the enchantment found within familial bonds.",
        "distributor": "Walt Disney",
        "year": "2020",
        "runtime": "1hr 42min",
        "rating": "88% match",
        "poster": "https://www.movieposters.com/cdn/shop/products/onward.125786.ar_480x.progressive.jpg?v=1573855877",
        "background": "https://images.wsj.net/im-161181?width=1280&size=1.77777778"

    },
    {
        "id": "3",
        "title": "Luca",
        "description": "Against the scenic Italian Riviera, a young sea monster named Luca forms an unlikely friendship during a transformative summer, challenging societal expectations and celebrating the power of authentic connections.",
        "distributor": "Walt Disney",
        "year": "2021",
        "runtime": "1hr 35min",
        "rating": "90% match",
        "poster":"https://cdn.shopify.com/s/files/1/0057/3728/3618/products/luca_uib9wgfd_500x749.jpg?v=1676653030",
        "background":"https://images.entertainment.ie/media/original_uAQrHntCccFpvxp75XdQgqexlJd.jpg?w=1280&h=768&q=high"
    },
    {
        "id": "4",
        "title": "Frozen",
        "description": "Within a magical kingdom, the bond between royal sisters is tested when one sister's magical powers inadvertently plunge their realm into eternal winter, exploring themes of self-acceptance and sisterhood.",
        "distributor": "Walt Disney",
        "year": "2013",
        "runtime": "1hr 42min",
        "rating": "92% match",
        "poster": "https://cdn.shopify.com/s/files/1/0057/3728/3618/products/9af69f74d0a34e3840d25107429f948a_cf87c688-bc12-4430-bf16-d9e3fa0f423a_500x749.jpg?v=1573592514",
        "background": "https://i0.wp.com/btr.michaelkwan.com/wp-content/uploads/2019/02/elsa.jpg?fit=1280%2C720&ssl=1"

    },
    {
        "id": "5",
        "title": "Aladdin",
        "description": "In the bustling city of Agrabah, a street-smart youth encounters a magical genie, embarking on a journey of self-discovery, love, and adventure amidst the vibrant Arabian nights.",
        "distributor": "Walt Disney",
        "year": "1992",
        "runtime": "1hr 30min",
        "rating": "90% match",
        "poster": "https://cdn.shopify.com/s/files/1/0057/3728/3618/products/45bfccb60aeb68a42e9133c56c1c8145_b51f412e-f8e4-4d95-aab7-b63ecfb882a1_500x749.jpg?v=1573585428",
        "background": "https://w.wallhaven.cc/full/x6/wallhaven-x6jw23.jpg"

    },
    {
        "id": "6",
        "title": "Rio",
        "description": "A rare blue macaw named Blu experiences a thrilling adventure in Rio de Janeiro, navigating the colorful and lively streets while discovering the true meaning of freedom.",
        "distributor": "20th Century Fox",
        "year": "2011",
        "runtime": "1hr 36min",
        "rating": "85% match",
        "poster": "https://cdn.shopify.com/s/files/1/0057/3728/3618/files/rio_ver3_xlg_500x749.jpg?v=1693405276",
        "background": "https://i0.wp.com/chasingsupermom.com/wp-content/uploads/2014/03/rio-2-still2.jpg?resize=1280%2C640&ssl=1"

    },
    {
        "id": "7",
        "title": "Soul",
        "description": "Navigating the afterlife, a passionate jazz musician named Joe Gardner explores profound questions of purpose, passion, and the joy found in life's ordinary moments, forming connections that transcend the boundaries of existence.",
        "distributor": "Walt Disney",
        "year": "2020",
        "runtime": "1hr 40min",
        "rating": "93% match",
        "poster":"https://cdn.shopify.com/s/files/1/0057/3728/3618/products/soul2020.adv.ar_500x749.jpg?v=1575580375",
        "background": "https://www.hdwallpapers.in/download/pixar_hd_soul-1280x720.jpg"

    }
]
